{
    "type": "FeatureCollection",
    "features": [
        {
            "type": "Feature",
            "geometry": {
                "type": "Polygon",
                "coordinates": [
                    [
                        [133.014295, 61.556752],
                        [132.985744, 61.565667],
                        [132.973959, 61.563918],
                        [132.965809, 61.564724],
                        [132.959313, 61.568596],
                        [132.953522, 61.569325],
                        [132.930345, 61.578981],
                        [132.90024, 61.583771],
                        [132.873517, 61.592606],
                        [132.854877, 61.603381],
                        [132.836602, 61.610046],
                        [132.829621, 61.603761],
                        [132.823807, 61.595464],
                        [132.807278, 61.581944],
                        [132.780347, 61.561158],
                        [132.773753, 61.55095],
                        [132.751596, 61.539647],
                        [132.728434, 61.516932],
                        [132.730219, 61.507619],
                        [132.72989, 61.499309],
                        [132.732011, 61.49469],
                        [132.741666, 61.483436],
                        [132.757664, 61.475715],
                        [132.771986, 61.471],
                        [132.773581, 61.466494],
                        [132.749759, 61.458424],
                        [132.621547, 61.454218],
                        [132.584172, 61.45246],
                        [132.55296, 61.44459],
                        [132.527653, 61.435195],
                        [132.51878, 61.434749],
                        [132.507163, 61.436812],
                        [132.484155, 61.430701],
                        [132.476922, 61.426788],
                        [132.471554, 61.41767],
                        [132.45926, 61.410687],
                        [132.448281, 61.410494],
                        [132.42383, 61.413339],
                        [132.379599, 61.414142],
                        [132.362311, 61.410564],
                        [132.357224, 61.40603],
                        [132.339387, 61.405479],
                        [132.327169, 61.399673],
                        [132.313455, 61.401475],
                        [132.298426, 61.406703],
                        [132.29305, 61.407125],
                        [132.286068, 61.405336],
                        [132.284439, 61.401842],
                        [132.2818, 61.401383],
                        [132.261268, 61.402027],
                        [132.255205, 61.399974],
                        [132.242096, 61.400494],
                        [132.231363, 61.396334],
                        [132.211575, 61.396824],
                        [132.194527, 61.402649],
                        [132.187559, 61.408725],
                        [132.168655, 61.409053],
                        [132.145476, 61.418166],
                        [132.1127, 61.423967],
                        [132.108868, 61.425355],
                        [132.106496, 61.43077],
                        [132.109703, 61.436346],
                        [132.104963, 61.442625],
                        [132.104961, 61.449045],
                        [132.110742, 61.455742],
                        [132.107069, 61.460182],
                        [132.110352, 61.467162],
                        [132.117138, 61.472501],
                        [132.129937, 61.476513],
                        [132.123721, 61.484265],
                        [132.096201, 61.486607],
                        [132.084305, 61.489617],
                        [132.057746, 61.490617],
                        [132.037429, 61.505821],
                        [132.008484, 61.507598],
                        [131.999302, 61.510129],
                        [131.978024, 61.509986],
                        [131.94151, 61.516744],
                        [131.90065, 61.533628],
                        [131.894178, 61.540901],
                        [131.890752, 61.553903],
                        [131.883468, 61.56055],
                        [131.884746, 61.564765],
                        [131.883369, 61.567184],
                        [131.869594, 61.57166],
                        [131.855349, 61.576045],
                        [131.849292, 61.580999],
                        [131.847015, 61.58888],
                        [131.833521, 61.59649],
                        [131.807318, 61.602297],
                        [131.780875, 61.612581],
                        [131.780081, 61.603918],
                        [131.782537, 61.593833],
                        [131.778117, 61.589998],
                        [131.728563, 61.584559],
                        [131.682868, 61.571376],
                        [131.666869, 61.570828],
                        [131.619117, 61.564561],
                        [131.613025, 61.565068],
                        [131.604943, 61.570276],
                        [131.599632, 61.571775],
                        [131.586534, 61.573909],
                        [131.5743, 61.57271],
                        [131.565099, 61.578099],
                        [131.555812, 61.580402],
                        [131.54584, 61.580621],
                        [131.539593, 61.577601],
                        [131.530708, 61.576084],
                        [131.523772, 61.572109],
                        [131.511032, 61.571149],
                        [131.509868, 61.572247],
                        [131.511471, 61.574676],
                        [131.507057, 61.576577],
                        [131.495211, 61.576094],
                        [131.492023, 61.577843],
                        [131.492681, 61.579034],
                        [131.488064, 61.579823],
                        [131.485879, 61.58179],
                        [131.483608, 61.581312],
                        [131.482881, 61.584372],
                        [131.484229, 61.586071],
                        [131.482161, 61.587311],
                        [131.46926, 61.586309],
                        [131.46216, 61.586851],
                        [131.458982, 61.588704],
                        [131.456085, 61.58722],
                        [131.433941, 61.593125],
                        [131.420078, 61.592925],
                        [131.401499, 61.585103],
                        [131.397862, 61.581056],
                        [131.397538, 61.577519],
                        [131.400719, 61.572816],
                        [131.415071, 61.56764],
                        [131.42834, 61.556858],
                        [131.422579, 61.548329],
                        [131.426696, 61.538932],
                        [131.420385, 61.533242],
                        [131.428656, 61.522777],
                        [131.425717, 61.518905],
                        [131.419226, 61.512869],
                        [131.397081, 61.509344],
                        [131.387974, 61.501468],
                        [131.375274, 61.497465],
                        [131.327312, 61.500348],
                        [131.319275, 61.499494],
                        [131.317598, 61.497978],
                        [131.318339, 61.495374],
                        [131.327362, 61.491231],
                        [131.329456, 61.488327],
                        [131.327895, 61.482447],
                        [131.322577, 61.480166],
                        [131.314136, 61.479521],
                        [131.313295, 61.475514],
                        [131.294709, 61.472044],
                        [131.28558, 61.464038],
                        [131.281309, 61.454637],
                        [131.281061, 61.449856],
                        [131.274971, 61.445481],
                        [131.278074, 61.442642],
                        [131.295843, 61.44037],
                        [131.301736, 61.437443],
                        [131.303435, 61.435862],
                        [131.302519, 61.434596],
                        [131.287622, 61.430531],
                        [131.286445, 61.428357],
                        [131.288552, 61.425389],
                        [131.287523, 61.423034],
                        [131.278341, 61.420953],
                        [131.259917, 61.420619],
                        [131.21946, 61.424823],
                        [131.203338, 61.422017],
                        [131.181554, 61.416429],
                        [131.161092, 61.408355],
                        [131.138595, 61.403592],
                        [131.113649, 61.40334],
                        [131.089135, 61.400421],
                        [131.071623, 61.400818],
                        [131.056036, 61.405507],
                        [131.018331, 61.407135],
                        [131.006539, 61.412233],
                        [130.996782, 61.413718],
                        [130.97249, 61.410506],
                        [130.952567, 61.402725],
                        [130.948553, 61.396243],
                        [130.942681, 61.370901],
                        [130.938111, 61.366073],
                        [130.926914, 61.361141],
                        [130.925608, 61.358982],
                        [130.927909, 61.352109],
                        [130.931452, 61.348647],
                        [130.931252, 61.345684],
                        [130.902286, 61.329745],
                        [130.856873, 61.304566],
                        [130.853521, 61.300288],
                        [130.851794, 61.293671],
                        [130.827782, 61.282648],
                        [130.823369, 61.266894],
                        [130.826592, 61.261575],
                        [130.825714, 61.257438],
                        [130.807324, 61.244125],
                        [130.804137, 61.240271],
                        [130.804815, 61.236432],
                        [130.813621, 61.226427],
                        [130.8147, 61.221338],
                        [130.814341, 61.20559],
                        [130.809325, 61.195857],
                        [130.783502, 61.184337],
                        [130.748707, 61.173561],
                        [130.728422, 61.161856],
                        [130.680711, 61.142774],
                        [130.678485, 61.139772],
                        [130.678953, 61.138769],
                        [130.68897, 61.132772],
                        [130.728495, 61.122146],
                        [130.759557, 61.110439],
                        [130.761324, 61.105366],
                        [130.758675, 61.102322],
                        [130.739416, 61.091831],
                        [130.712369, 61.083743],
                        [130.705192, 61.078208],
                        [130.699754, 61.069208],
                        [130.706053, 61.051483],
                        [130.712379, 61.044498],
                        [130.72209, 61.041922],
                        [130.747611, 61.045002],
                        [130.754623, 61.044362],
                        [130.758464, 61.04051],
                        [130.75355, 61.030997],
                        [130.754323, 61.029532],
                        [130.778789, 61.018084],
                        [130.783113, 61.013176],
                        [130.782555, 61.00445],
                        [130.789821, 61.000434],
                        [130.78278, 60.992944],
                        [130.779176, 60.986225],
                        [130.790976, 60.977206],
                        [130.808378, 60.969881],
                        [130.808754, 60.96452],
                        [130.818069, 60.95613],
                        [130.818935, 60.948642],
                        [130.833824, 60.941486],
                        [130.835231, 60.940094],
                        [130.835537, 60.933609],
                        [130.841303, 60.929312],
                        [130.843188, 60.924948],
                        [130.850997, 60.919739],
                        [130.850129, 60.915755],
                        [130.839583, 60.908733],
                        [130.839865, 60.904985],
                        [130.846573, 60.896338],
                        [130.843128, 60.892128],
                        [130.830381, 60.886544],
                        [130.832312, 60.879829],
                        [130.829621, 60.873173],
                        [130.833709, 60.866138],
                        [130.823069, 60.859979],
                        [130.820061, 60.851896],
                        [130.805362, 60.849959],
                        [130.804027, 60.846068],
                        [130.806488, 60.842428],
                        [130.792365, 60.834298],
                        [130.800687, 60.830165],
                        [130.806348, 60.823428],
                        [130.820234, 60.815955],
                        [130.81985, 60.813412],
                        [130.81107, 60.8073],
                        [130.820624, 60.798555],
                        [130.824481, 60.792718],
                        [130.82361, 60.780316],
                        [130.828148, 60.776875],
                        [130.801494, 60.768252],
                        [130.80032, 60.765288],
                        [130.804126, 60.756427],
                        [130.803025, 60.752184],
                        [130.794038, 60.746039],
                        [130.704312, 60.748048],
                        [130.691055, 60.744374],
                        [130.679544, 60.735612],
                        [130.663682, 60.731],
                        [130.638755, 60.734638],
                        [130.613413, 60.743648],
                        [130.576489, 60.752057],
                        [130.573251, 60.754077],
                        [130.567801, 60.761809],
                        [130.561389, 60.765488],
                        [130.561205, 60.767275],
                        [130.567636, 60.774407],
                        [130.565105, 60.777941],
                        [130.565732, 60.779719],
                        [130.579462, 60.783922],
                        [130.580499, 60.785761],
                        [130.570561, 60.797195],
                        [130.569706, 60.808435],
                        [130.560965, 60.814171],
                        [130.543017, 60.807025],
                        [130.5352, 60.800236],
                        [130.522843, 60.793502],
                        [130.513395, 60.79219],
                        [130.510077, 60.788157],
                        [130.501373, 60.785678],
                        [130.470827, 60.783172],
                        [130.44855, 60.778413],
                        [130.414566, 60.773926],
                        [130.383808, 60.766805],
                        [130.33914, 60.763684],
                        [130.316047, 60.760402],
                        [130.279651, 60.75042],
                        [130.272507, 60.752408],
                        [130.275389, 60.763744],
                        [130.268091, 60.776794],
                        [130.268589, 60.789797],
                        [130.260116, 60.793245],
                        [130.234927, 60.797487],
                        [130.224624, 60.793451],
                        [130.223918, 60.7871],
                        [130.220097, 60.783664],
                        [130.218467, 60.779682],
                        [130.200197, 60.774413],
                        [130.188424, 60.767019],
                        [130.174816, 60.762616],
                        [130.156639, 60.7595],
                        [130.110935, 60.761687],
                        [130.091563, 60.752783],
                        [130.073768, 60.750368],
                        [130.030397, 60.735641],
                        [129.988905, 60.745903],
                        [129.990973, 60.752711],
                        [129.989638, 60.755693],
                        [129.98075, 60.762444],
                        [129.973817, 60.764882],
                        [129.982747, 60.781679],
                        [129.995391, 60.798359],
                        [129.995486, 60.801404],
                        [129.986563, 60.813329],
                        [129.977891, 60.819062],
                        [129.968921, 60.822749],
                        [129.957359, 60.823238],
                        [129.94945, 60.820175],
                        [129.945424, 60.816776],
                        [129.938976, 60.815903],
                        [129.939108, 60.811882],
                        [129.934054, 60.805549],
                        [129.919447, 60.794766],
                        [129.91091, 60.783257999999996],
                        [129.899548, 60.778559],
                        [129.898511, 60.77119],
                        [129.886789, 60.762975],
                        [129.885827, 60.761195],
                        [129.888481, 60.755126],
                        [129.884878, 60.74654],
                        [129.886026, 60.7388],
                        [129.879801, 60.72907],
                        [129.878387, 60.722865],
                        [129.873556, 60.718998],
                        [129.866287, 60.716877],
                        [129.850892, 60.717787],
                        [129.833217, 60.715713],
                        [129.797312, 60.716671],
                        [129.786894, 60.714336],
                        [129.760642, 60.704148],
                        [129.735282, 60.701065],
                        [129.709306, 60.70287],
                        [129.684509, 60.713517],
                        [129.685265, 60.722399],
                        [129.679395, 60.726457],
                        [129.677483, 60.74198],
                        [129.657086, 60.74659],
                        [129.642999, 60.753139],
                        [129.636303, 60.76131],
                        [129.631301, 60.76446],
                        [129.633581, 60.77046],
                        [129.628079, 60.777877],
                        [129.631278, 60.783401],
                        [129.629808, 60.785707],
                        [129.623692, 60.787319],
                        [129.610688, 60.787468],
                        [129.599289, 60.792766],
                        [129.599645, 60.803063],
                        [129.593158, 60.807316],
                        [129.590912, 60.811752],
                        [129.602801, 60.81693],
                        [129.604301, 60.819733],
                        [129.598034, 60.825252],
                        [129.596263, 60.832034],
                        [129.586837, 60.838979],
                        [129.59468, 60.844589],
                        [129.594297, 60.850845],
                        [129.599624, 60.855288],
                        [129.599518, 60.858537],
                        [129.584014, 60.86287],
                        [129.551687, 60.865735],
                        [129.532915, 60.869636],
                        [129.51269, 60.876773],
                        [129.504856, 60.876575],
                        [129.478889, 60.871537],
                        [129.438215, 60.873267],
                        [129.417904, 60.870473],
                        [129.405467, 60.867018],
                        [129.359948, 60.861324],
                        [129.355457, 60.863261],
                        [129.352332, 60.866892],
                        [129.345455, 60.868567],
                        [129.346379, 60.870903],
                        [129.351782, 60.874398],
                        [129.35101, 60.876966],
                        [129.345743, 60.881642],
                        [129.343801, 60.887007],
                        [129.326402, 60.891664],
                        [129.31998, 60.896528],
                        [129.314826, 60.906489],
                        [129.311926, 60.908364],
                        [129.260938, 60.913914],
                        [129.241421, 60.913869],
                        [129.228355, 60.917871],
                        [129.210417, 60.91721],
                        [129.187065, 60.922922],
                        [129.17808, 60.922008],
                        [129.164691, 60.913903],
                        [129.125384, 60.907611],
                        [129.118366, 60.904003],
                        [129.117269, 60.900593],
                        [129.121113, 60.884549],
                        [129.117944, 60.880085],
                        [129.101942, 60.87827],
                        [129.100012, 60.873764],
                        [129.086996, 60.865814],
                        [129.060743, 60.854945],
                        [129.056835, 60.856035],
                        [129.053514, 60.861429],
                        [129.049934, 60.863762],
                        [129.037865, 60.867745],
                        [129.001371, 60.871539],
                        [128.951757, 60.864209],
                        [128.938184, 60.863594],
                        [128.929018, 60.860268],
                        [128.922217, 60.854977],
                        [128.91639, 60.854892],
                        [128.911059, 60.856066],
                        [128.90205, 60.861745],
                        [128.893186, 60.873149],
                        [128.8771, 60.876409],
                        [128.85068, 60.889848],
                        [128.820986, 60.893912],
                        [128.828051, 60.888148],
                        [128.827308, 60.886766],
                        [128.829236, 60.884657],
                        [128.828352, 60.878564],
                        [128.8322, 60.875645],
                        [128.832548, 60.872722],
                        [128.829059, 60.871053],
                        [128.829412, 60.867358],
                        [128.827509, 60.865081],
                        [128.816588, 60.85835],
                        [128.817565, 60.856435],
                        [128.813327, 60.852254],
                        [128.812221, 60.847834],
                        [128.81576, 60.846117],
                        [128.818321, 60.840631],
                        [128.815671, 60.83845],
                        [128.816139, 60.832262],
                        [128.813883, 60.831041],
                        [128.814797, 60.828394],
                        [128.81281, 60.826735],
                        [128.81438, 60.825681],
                        [128.812988, 60.824834],
                        [128.813135, 60.822366],
                        [128.816775, 60.820015],
                        [128.814891, 60.81795],
                        [128.809312, 60.816415],
                        [128.810666, 60.815247],
                        [128.808262, 60.814026],
                        [128.808409, 60.811687],
                        [128.809691, 60.811437],
                        [128.806542, 60.809711],
                        [128.804656, 60.805468],
                        [128.807135, 60.805163],
                        [128.805403, 60.80287],
                        [128.80876, 60.800317],
                        [128.804166, 60.798572],
                        [128.803244, 60.79719],
                        [128.804703, 60.794999],
                        [128.799234, 60.789923],
                        [128.802581, 60.78075],
                        [128.801564, 60.778637],
                        [128.80594, 60.774566],
                        [128.803164, 60.772337],
                        [128.812021, 60.768614],
                        [128.807582, 60.766691],
                        [128.808722, 60.76484],
                        [128.811946, 60.764293],
                        [128.80788, 60.761379],
                        [128.808487, 60.759788],
                        [128.811842, 60.759387],
                        [128.81009, 60.758215],
                        [128.812317, 60.757682],
                        [128.810561, 60.757144],
                        [128.812795, 60.755376],
                        [128.809917, 60.753813],
                        [128.811946, 60.752955],
                        [128.810168, 60.750629],
                        [128.812071, 60.748715],
                        [128.810017, 60.747997],
                        [128.815518, 60.743668],
                        [128.814607, 60.740597],
                        [128.816076, 60.738991],
                        [128.813396, 60.737785],
                        [128.815929, 60.735742],
                        [128.818649, 60.735859],
                        [128.819361, 60.733066],
                        [128.813439, 60.730345],
                        [128.814844, 60.728317],
                        [128.812268, 60.72638],
                        [128.816188, 60.725313],
                        [128.813409, 60.724026],
                        [128.815558, 60.719384],
                        [128.810289, 60.718938],
                        [128.814438, 60.718099],
                        [128.812624, 60.716423],
                        [128.813524, 60.715645],
                        [128.805874, 60.708698],
                        [128.80622, 60.706375],
                        [128.803672, 60.705673],
                        [128.805001, 60.705139],
                        [128.803347, 60.704503],
                        [128.808154, 60.704348],
                        [128.80909, 60.703082],
                        [128.805421, 60.701452],
                        [128.806226, 60.699748],
                        [128.803145, 60.69963],
                        [128.802168, 60.696834],
                        [128.799552, 60.696522],
                        [128.800651, 60.695695],
                        [128.798944, 60.693109],
                        [128.792292, 60.691946],
                        [128.794765, 60.68862],
                        [128.797552, 60.687909],
                        [128.798642, 60.683119],
                        [128.790656, 60.678688],
                        [128.793685, 60.676191],
                        [128.792475, 60.673915],
                        [128.794134, 60.673382],
                        [128.792495, 60.670732],
                        [128.795043, 60.670979],
                        [128.791706, 60.669951],
                        [128.793859, 60.667404],
                        [128.789465, 60.66319],
                        [128.790815, 60.659245],
                        [128.785425, 60.653534],
                        [128.787351, 60.652498],
                        [128.786401, 60.651034],
                        [128.787768, 60.649477],
                        [128.784553, 60.650268],
                        [128.784402, 60.648237],
                        [128.771022, 60.640775],
                        [128.772855, 60.638731],
                        [128.771411, 60.637218],
                        [128.773835, 60.635858],
                        [128.771339, 60.633303],
                        [128.773459, 60.632803],
                        [128.773606, 60.630724],
                        [128.770271, 60.630069],
                        [128.772791, 60.629147],
                        [128.771021, 60.626821],
                        [128.772582, 60.625947],
                        [128.767692, 60.620805],
                        [128.770008, 60.620566],
                        [128.770337, 60.616197],
                        [128.768826, 60.614846],
                        [128.772546, 60.612302],
                        [128.768845, 60.612182],
                        [128.767596, 60.611189],
                        [128.769848, 60.610543],
                        [128.765923, 60.609529],
                        [128.766952, 60.608848],
                        [128.764028, 60.606488],
                        [128.760417, 60.607732],
                        [128.756349, 60.603842],
                        [128.75103, 60.603768],
                        [128.749581, 60.599241],
                        [128.773275, 60.593135],
                        [128.774271, 60.592422],
                        [128.773059, 60.590974],
                        [128.776639, 60.589047],
                        [128.773855, 60.585777],
                        [128.765279, 60.584463],
                        [128.766581, 60.582435],
                        [128.760103, 60.578833],
                        [128.763873, 60.57806],
                        [128.772363, 60.572568],
                        [128.770009, 60.56938],
                        [128.764145, 60.567875],
                        [128.76272, 60.564153],
                        [128.766938, 60.564989],
                        [128.767186, 60.56265],
                        [128.770635, 60.560203],
                        [128.780036, 60.555768],
                        [128.779716, 60.554322],
                        [128.77394, 60.554799],
                        [128.78061, 60.548979],
                        [128.78662, 60.548046],
                        [128.787192, 60.551231],
                        [128.788851, 60.549723],
                        [128.799437, 60.550194],
                        [128.800322, 60.540335],
                        [128.805162, 60.536086],
                        [128.804325, 60.532836],
                        [128.807857, 60.532046],
                        [128.806622, 60.529055],
                        [128.822622, 60.526835],
                        [128.824181, 60.525115],
                        [128.820993, 60.523471],
                        [128.824867, 60.520097],
                        [128.822982, 60.515205],
                        [128.834884, 60.513937],
                        [128.841062, 60.510565],
                        [128.824847, 60.505509],
                        [128.826213, 60.502603],
                        [128.831641, 60.503975],
                        [128.833957, 60.501964],
                        [128.831825, 60.500198],
                        [128.837735, 60.500661],
                        [128.84868, 60.494785],
                        [128.847602, 60.492867],
                        [128.844343, 60.492684],
                        [128.846465, 60.4896],
                        [128.844825, 60.488461],
                        [128.84512, 60.485774],
                        [128.840537, 60.48329],
                        [128.846081, 60.480373],
                        [128.842069, 60.479686],
                        [128.843196, 60.478063],
                        [128.842285, 60.47582],
                        [128.849251, 60.471166],
                        [128.867428, 60.467871],
                        [128.873823, 60.464791],
                        [128.87074, 60.462482],
                        [128.868735, 60.454016],
                        [128.864473, 60.450731],
                        [128.846111, 60.446341],
                        [128.843327, 60.444047],
                        [128.850576, 60.440563],
                        [128.867971, 60.439509],
                        [128.86663, 60.437867],
                        [128.868277, 60.43717],
                        [128.873824, 60.439174],
                        [128.877319, 60.436513],
                        [128.878052, 60.433849],
                        [128.872702, 60.423675],
                        [128.874845, 60.421647],
                        [128.873569, 60.420265],
                        [128.879062, 60.418564],
                        [128.882702, 60.420354],
                        [128.881885, 60.419151],
                        [128.884096, 60.416424],
                        [128.882689, 60.414994],
                        [128.885189, 60.413989],
                        [128.867999, 60.408368],
                        [128.874062, 60.40316],
                        [128.891787, 60.39554],
                        [128.889809, 60.388147],
                        [128.894342, 60.387063],
                        [128.896025, 60.384172],
                        [128.891371, 60.382577],
                        [128.894922, 60.380403],
                        [128.898529, 60.38125],
                        [128.895293, 60.377219],
                        [128.900381, 60.376508],
                        [128.894677, 60.375042],
                        [128.892849, 60.372133],
                        [128.900027, 60.374104],
                        [128.907254, 60.371039],
                        [128.902175, 60.369167],
                        [128.904674, 60.366846],
                        [128.905209, 60.363354],
                        [128.914387, 60.365455],
                        [128.915081, 60.363588],
                        [128.908099, 60.362007],
                        [128.908827, 60.359717],
                        [128.916864, 60.358943],
                        [128.914409, 60.357073],
                        [128.915231, 60.356083],
                        [128.921329, 60.356533],
                        [128.920644, 60.355225],
                        [128.912432, 60.354643],
                        [128.922072, 60.347648],
                        [128.921521, 60.34504],
                        [128.916766, 60.345703],
                        [128.916245, 60.344574],
                        [128.922771, 60.343221],
                        [128.912425, 60.338926],
                        [128.914644, 60.336296],
                        [128.912746, 60.335361],
                        [128.913061, 60.33372],
                        [128.93069, 60.333723],
                        [128.935986, 60.33176],
                        [128.93501, 60.328348],
                        [128.914553, 60.314755],
                        [128.918358, 60.312248],
                        [128.92794, 60.310426],
                        [128.938417, 60.302228],
                        [128.928009, 60.30154],
                        [128.922484, 60.298426],
                        [128.92299, 60.28526],
                        [128.929375, 60.282892],
                        [128.945323, 60.283476],
                        [128.947798, 60.280772],
                        [128.945242, 60.273339],
                        [128.950534, 60.266851],
                        [128.953257, 60.26059],
                        [128.950825, 60.258014],
                        [128.956356, 60.254028],
                        [128.950851, 60.251662],
                        [128.956069, 60.248147],
                        [128.939962, 60.245339],
                        [128.944936, 60.241556],
                        [128.956817, 60.23901],
                        [128.966014, 60.239321],
                        [128.973003, 60.242458],
                        [128.976843, 60.242126],
                        [128.976584, 60.238722],
                        [128.970477, 60.235123],
                        [128.95671, 60.233543],
                        [128.945585, 60.234376],
                        [128.941553, 60.233196],
                        [128.944021, 60.231833],
                        [128.94373, 60.230102],
                        [128.93643, 60.230132],
                        [128.932212, 60.224208],
                        [128.932358, 60.21702],
                        [128.934195, 60.212732],
                        [128.931933, 60.209531],
                        [128.937695, 60.200802],
                        [128.946137, 60.197142],
                        [128.958131, 60.195425],
                        [128.965085, 60.191755],
                        [128.961077, 60.187092],
                        [128.946899, 60.180004],
                        [128.945436, 60.176965],
                        [128.957082, 60.173867],
                        [128.976956, 60.174587],
                        [128.980202, 60.172313],
                        [128.979455, 60.167634],
                        [128.971424, 60.16176],
                        [128.970286, 60.158665],
                        [128.967532, 60.158039],
                        [128.966691, 60.152499],
                        [128.967901, 60.147675],
                        [128.975934, 60.145646],
                        [128.975887, 60.143542],
                        [128.977581, 60.142925],
                        [128.994326, 60.141928],
                        [128.998236, 60.136989],
                        [128.995614, 60.132603],
                        [128.984251, 60.12651],
                        [128.986304, 60.122335],
                        [128.991514, 60.120126],
                        [128.997179, 60.113929],
                        [129.00361, 60.112654],
                        [129.004795, 60.109185],
                        [129.001752, 60.103564],
                        [129.003264, 60.099324],
                        [129.001979, 60.09761],
                        [128.993229, 60.093443],
                        [128.994074, 60.094727],
                        [128.992269, 60.095799],
                        [128.987731, 60.094686],
                        [128.996352, 60.087262],
                        [128.989604, 60.08848],
                        [128.989067, 60.08727],
                        [128.996597, 60.083582],
                        [129.000222, 60.085101],
                        [129.008807, 60.083907],
                        [129.018271, 60.085385],
                        [129.020092, 60.084068],
                        [129.01944, 60.081778],
                        [129.008188, 60.076337],
                        [129.000938, 60.076175],
                        [129.010103, 60.067304],
                        [129.004318, 60.068945],
                        [129.003538, 60.067142],
                        [129.01949, 60.056126],
                        [129.014096, 60.056111],
                        [129.017442, 60.053885],
                        [129.013316, 60.053284],
                        [129.014419, 60.051188],
                        [129.021759, 60.048166],
                        [129.024002, 60.050358],
                        [129.025431, 60.049773],
                        [129.024551, 60.04581],
                        [129.027051, 60.044509],
                        [129.024582, 60.043032],
                        [129.025423, 60.039587],
                        [129.029417, 60.038287],
                        [129.030195, 60.036516],
                        [129.026523, 60.033381],
                        [129.033915, 60.02295],
                        [129.038068, 60.021649],
                        [129.039751, 60.01749],
                        [129.037479, 60.017393],
                        [129.0379, 60.016045],
                        [129.047337, 60.011834],
                        [129.052692, 60.012579],
                        [129.061884, 60.017108],
                        [129.071651, 60.016388],
                        [129.075411, 60.014485],
                        [129.076314, 60.011853],
                        [129.074619, 60.008507],
                        [129.067474, 60.005165],
                        [129.071949, 60.004399],
                        [129.066711, 59.996733999999996],
                        [129.074816, 59.99517],
                        [129.097596, 60.005024],
                        [129.103412, 60.002623],
                        [129.099995, 59.999068],
                        [129.097239, 59.999582],
                        [129.096568, 59.997592],
                        [129.092563, 59.997506],
                        [129.096514, 59.995456],
                        [129.088568, 59.989475],
                        [129.093061, 59.984493],
                        [129.109071, 59.982499],
                        [129.112591, 59.983145],
                        [129.110148, 59.984699],
                        [129.114527, 59.985369],
                        [129.116642, 59.98289],
                        [129.121827, 59.982333],
                        [129.136818, 59.985535],
                        [129.14573, 59.984535],
                        [129.134359, 59.982638],
                        [129.12997, 59.979596],
                        [129.126787, 59.973751],
                        [129.127085, 59.966805],
                        [129.14688, 59.954885],
                        [129.164264, 59.949487],
                        [129.182357, 59.941397],
                        [129.186419, 59.929695],
                        [129.182749, 59.924339],
                        [129.168956, 59.916681],
                        [129.158842, 59.916125],
                        [129.147897, 59.917843],
                        [129.148703, 59.909963],
                        [129.152643, 59.904923],
                        [129.159338, 59.901503],
                        [129.180094, 59.897252],
                        [129.204411, 59.894618],
                        [129.211655, 59.879579],
                        [129.225571, 59.877557],
                        [129.245671, 59.866401],
                        [129.248864, 59.861278],
                        [129.245664, 59.85446],
                        [129.289905, 59.835566],
                        [129.297374, 59.829749],
                        [129.302297, 59.82103],
                        [129.313963, 59.812798],
                        [129.316714, 59.806943],
                        [129.32134, 59.803374],
                        [129.354614, 59.79848],
                        [129.405887, 59.778072],
                        [129.409231, 59.774813],
                        [129.410468, 59.750927],
                        [129.415334, 59.747378],
                        [129.426724, 59.744417],
                        [129.449988, 59.744949],
                        [129.463242, 59.749005],
                        [129.476948, 59.750662],
                        [129.487626, 59.759883],
                        [129.513835, 59.762708],
                        [129.526802, 59.775191],
                        [129.535469, 59.779233],
                        [129.542074, 59.77919],
                        [129.553395, 59.77206],
                        [129.576981, 59.766662],
                        [129.613527, 59.762467],
                        [129.625929, 59.762588],
                        [129.65296, 59.766339],
                        [129.665931, 59.772302],
                        [129.669532, 59.7768],
                        [129.674291, 59.779489],
                        [129.707078, 59.78177],
                        [129.73546, 59.785765],
                        [129.739142, 59.788279],
                        [129.744377, 59.801866],
                        [129.752435, 59.805369],
                        [129.773132, 59.809245],
                        [129.790839, 59.810602],
                        [129.823946, 59.809912],
                        [129.845445, 59.811904],
                        [129.853919, 59.81029],
                        [129.863154, 59.800692],
                        [129.874392, 59.795159],
                        [129.91626, 59.791828],
                        [129.923595, 59.788373],
                        [129.929535, 59.778274],
                        [129.944039, 59.774986],
                        [129.951023, 59.771313],
                        [129.95452, 59.768525],
                        [129.95548, 59.76379],
                        [129.939248, 59.756954],
                        [129.933667, 59.751997],
                        [129.938881, 59.745031],
                        [129.955476, 59.737129],
                        [129.975591, 59.737712],
                        [130.001818, 59.732218],
                        [130.026761, 59.729182],
                        [130.038878, 59.729786],
                        [130.056879, 59.727156],
                        [130.064855, 59.728083],
                        [130.084708, 59.736044],
                        [130.087726, 59.738798],
                        [130.082741, 59.746881],
                        [130.08548, 59.760848],
                        [130.084769, 59.766744],
                        [130.086293, 59.770021],
                        [130.115428, 59.775675],
                        [130.139241, 59.786601],
                        [130.148469, 59.785465],
                        [130.160232, 59.777514],
                        [130.167365, 59.779693],
                        [130.178574, 59.777724],
                        [130.195584, 59.770389],
                        [130.208539, 59.762472],
                        [130.220116, 59.760188],
                        [130.229332, 59.760321],
                        [130.249169, 59.765415],
                        [130.256764, 59.768665],
                        [130.263444, 59.774077],
                        [130.272262, 59.775486],
                        [130.278783, 59.77916],
                        [130.293528, 59.779634],
                        [130.301669, 59.776824],
                        [130.310219, 59.765592],
                        [130.311203, 59.761927],
                        [130.306137, 59.757574],
                        [130.314905, 59.754497],
                        [130.318103, 59.751491],
                        [130.315485, 59.747147],
                        [130.300946, 59.740841],
                        [130.299316, 59.737835],
                        [130.301672, 59.734277],
                        [130.31767, 59.729836],
                        [130.319347, 59.724214],
                        [130.329956, 59.715918],
                        [130.341628, 59.711388],
                        [130.351263, 59.711443],
                        [130.359932, 59.709501],
                        [130.366506, 59.710635],
                        [130.38068, 59.704955],
                        [130.395068, 59.706078],
                        [130.41003, 59.703237],
                        [130.455574, 59.699848],
                        [130.484807, 59.700008],
                        [130.490526, 59.703551],
                        [130.492639, 59.710562],
                        [130.499689, 59.714301],
                        [130.502158, 59.717717],
                        [130.531863, 59.714856],
                        [130.566134, 59.71619],
                        [130.574042, 59.718825],
                        [130.574617, 59.726253],
                        [130.572294, 59.731602],
                        [130.577225, 59.73723],
                        [130.575582, 59.739931],
                        [130.581804, 59.743878],
                        [130.592901, 59.745369],
                        [130.597282, 59.752831],
                        [130.59659, 59.755196],
                        [130.589333, 59.758371],
                        [130.587995, 59.760703],
                        [130.593225, 59.764011],
                        [130.594229, 59.768516],
                        [130.598753, 59.771825],
                        [130.59373, 59.783057],
                        [130.600383, 59.790735],
                        [130.611773, 59.796284],
                        [130.63641, 59.802235],
                        [130.662882, 59.802757],
                        [130.666252, 59.805663],
                        [130.674665, 59.81971],
                        [130.678778, 59.821932],
                        [130.68397, 59.821866],
                        [130.691089, 59.81716],
                        [130.69276, 59.812556],
                        [130.705792, 59.806229],
                        [130.752035, 59.802323],
                        [130.767259, 59.810861],
                        [130.768656, 59.81289],
                        [130.767738, 59.816867],
                        [130.770413, 59.818635],
                        [130.807059, 59.816057],
                        [130.820889, 59.820579],
                        [130.825929, 59.824799],
                        [130.833636, 59.826447],
                        [130.835634, 59.829328],
                        [130.833211, 59.835748],
                        [130.839571, 59.842192],
                        [130.832672, 59.847683],
                        [130.831327, 59.852008],
                        [130.836704, 59.856378],
                        [130.851614, 59.860174],
                        [130.845599, 59.865914],
                        [130.850075, 59.870872],
                        [130.850073, 59.873732],
                        [130.833129, 59.878292],
                        [130.833586, 59.880723],
                        [130.842698, 59.888233],
                        [130.869077, 59.895597],
                        [130.87267, 59.903687],
                        [130.87654, 59.905761],
                        [130.899054, 59.908526],
                        [130.903461, 59.9109],
                        [130.904428, 59.920441],
                        [130.897312, 59.921096],
                        [130.881381, 59.928426],
                        [130.882499, 59.932164],
                        [130.887768, 59.937126],
                        [130.888678, 59.942882],
                        [130.898923, 59.945319],
                        [130.921384, 59.946951],
                        [130.930009, 59.950441],
                        [130.937077, 59.954969],
                        [130.94013, 59.960084],
                        [130.939175, 59.964526],
                        [130.935673, 59.968396],
                        [130.950895, 59.970935],
                        [130.973553, 59.981242],
                        [130.985638, 59.982686],
                        [131.005806, 59.978359],
                        [131.015509, 59.980608],
                        [131.019847, 59.989276],
                        [131.029525, 59.993719],
                        [131.03697, 60.000701],
                        [131.037061, 60.003109],
                        [131.033138, 60.008971],
                        [131.035847, 60.012391],
                        [131.0457, 60.016627],
                        [131.043905, 60.025673],
                        [131.046175, 60.028238],
                        [131.061502, 60.032924],
                        [131.083425, 60.037033],
                        [131.126147, 60.040911],
                        [131.136504, 60.046586],
                        [131.141515, 60.054225],
                        [131.152813, 60.060022],
                        [131.171986, 60.056214],
                        [131.18677, 60.050485],
                        [131.19557, 60.05038],
                        [131.208203, 60.052445],
                        [131.21522, 60.057487],
                        [131.225652, 60.059141],
                        [131.257332, 60.058701],
                        [131.263292, 60.056486],
                        [131.266116, 60.053594],
                        [131.272898, 60.053664],
                        [131.279447, 60.056721],
                        [131.289921, 60.05801],
                        [131.29418, 60.064851],
                        [131.305191, 60.064644],
                        [131.323717, 60.059932],
                        [131.325157, 60.05499],
                        [131.336096, 60.050864],
                        [131.336461, 60.048209],
                        [131.332735, 60.043764],
                        [131.341602, 60.037066],
                        [131.358002, 60.031289],
                        [131.359343, 60.029599],
                        [131.35641, 60.026036],
                        [131.377557, 60.027688],
                        [131.386807, 60.03616],
                        [131.396353, 60.039457],
                        [131.404241, 60.033991],
                        [131.405687, 60.030429],
                        [131.411498, 60.025488],
                        [131.440324, 60.01628],
                        [131.43658, 60.011961],
                        [131.438952, 60.008024],
                        [131.460851, 60.003937],
                        [131.459319, 59.993807],
                        [131.469271, 59.990208],
                        [131.468497, 59.982421],
                        [131.462797, 59.97948],
                        [131.474035, 59.971883],
                        [131.473878, 59.959566],
                        [131.487669, 59.958697],
                        [131.500833, 59.951028],
                        [131.516283, 59.947516],
                        [131.518372, 59.946436],
                        [131.519501, 59.94253],
                        [131.527429, 59.937096],
                        [131.539325, 59.936989],
                        [131.551794, 59.943291],
                        [131.555803, 59.947813],
                        [131.56681, 59.951045],
                        [131.568323, 59.955932],
                        [131.593381, 59.958286],
                        [131.595999, 59.960673],
                        [131.595737, 59.964579],
                        [131.599936, 59.966447],
                        [131.61347, 59.966423],
                        [131.623098, 59.968264],
                        [131.635676, 59.962324],
                        [131.643425, 59.96091],
                        [131.658005, 59.964469],
                        [131.682757, 59.955239],
                        [131.694975, 59.949057],
                        [131.694868, 59.946133],
                        [131.684316, 59.943472],
                        [131.705001, 59.928143],
                        [131.708544, 59.923332],
                        [131.717089, 59.921116],
                        [131.726, 59.91608],
                        [131.736629, 59.916795],
                        [131.748084, 59.914183],
                        [131.753478, 59.910917],
                        [131.755176, 59.906216],
                        [131.776487, 59.911247],
                        [131.796193, 59.907701],
                        [131.817253, 59.908724],
                        [131.822231, 59.911706],
                        [131.826542, 59.917481],
                        [131.828891, 59.917683],
                        [131.84672, 59.912658],
                        [131.848652, 59.909138],
                        [131.86014, 59.904223],
                        [131.857918, 59.897948],
                        [131.859107, 59.893899],
                        [131.857627, 59.891736],
                        [131.861432, 59.888029],
                        [131.863172, 59.880619],
                        [131.881643, 59.875632],
                        [131.883845, 59.873795],
                        [131.885341, 59.8683],
                        [131.891132, 59.866125],
                        [131.893896, 59.862585],
                        [131.909211, 59.858078],
                        [131.911411, 59.859208],
                        [131.900657, 59.865249],
                        [131.901958, 59.874243],
                        [131.916629, 59.8852],
                        [131.918673, 59.88952],
                        [131.933222, 59.905738],
                        [131.937913, 59.915241],
                        [131.943538, 59.922447],
                        [131.95351, 59.929718],
                        [131.952991, 59.932981],
                        [131.942676, 59.944705],
                        [131.947551, 59.950887],
                        [131.945321, 59.957163],
                        [131.987322, 59.966582],
                        [131.999704, 59.976318],
                        [132.028731, 59.985642],
                        [132.029425, 59.989794],
                        [132.033218, 59.991335],
                        [132.033248, 59.993852],
                        [132.038485, 59.994298],
                        [132.045038, 60.000143],
                        [132.044613, 60.005167],
                        [132.042077, 60.009721],
                        [132.039609, 60.010942],
                        [132.036931, 60.017504],
                        [132.039788, 60.025783],
                        [132.061095, 60.041379],
                        [132.071964, 60.054646],
                        [132.075594, 60.066739],
                        [132.082896, 60.082702],
                        [132.089434, 60.092639],
                        [132.092468, 60.094355],
                        [132.092156, 60.097843],
                        [132.094422, 60.098698],
                        [132.095779, 60.105098],
                        [132.09916, 60.108327],
                        [132.092671, 60.118477],
                        [132.091986, 60.127841],
                        [132.094356, 60.134687],
                        [132.099955, 60.142338],
                        [132.10876, 60.163482],
                        [132.117866, 60.177811],
                        [132.11777, 60.179894],
                        [132.113358, 60.183103],
                        [132.096237, 60.188983],
                        [132.092329, 60.195305],
                        [132.072676, 60.203057],
                        [132.070434, 60.2051],
                        [132.066958, 60.214561],
                        [132.060283, 60.217629],
                        [132.054769, 60.224019],
                        [132.054474, 60.226781],
                        [132.061152, 60.230082],
                        [132.082984, 60.232828],
                        [132.100895, 60.238149],
                        [132.105373, 60.241759],
                        [132.133666, 60.256205],
                        [132.145095, 60.266209],
                        [132.152321, 60.270224],
                        [132.165547, 60.273144],
                        [132.186283, 60.272973],
                        [132.19734, 60.27391],
                        [132.203713, 60.271643],
                        [132.208522, 60.272283],
                        [132.212269, 60.274607],
                        [132.213217, 60.278429],
                        [132.220382, 60.285215],
                        [132.235387, 60.293563],
                        [132.258852, 60.299118],
                        [132.279773, 60.300602],
                        [132.285294, 60.303734],
                        [132.293283, 60.325794],
                        [132.291045, 60.334174],
                        [132.29412, 60.340601],
                        [132.291092, 60.346676],
                        [132.297741, 60.353714],
                        [132.303184, 60.356261],
                        [132.303875, 60.366649],
                        [132.308146, 60.369925],
                        [132.305776, 60.376016],
                        [132.317797, 60.380791],
                        [132.319118, 60.38869],
                        [132.318146, 60.398827],
                        [132.315661, 60.403783],
                        [132.327284, 60.413004],
                        [132.326992, 60.416898],
                        [132.323176, 60.424421],
                        [132.326805, 60.428308],
                        [132.318057, 60.433265],
                        [132.334865, 60.44155],
                        [132.332565, 60.445634],
                        [132.341345, 60.455634],
                        [132.34218, 60.458803],
                        [132.336372, 60.463488],
                        [132.335821, 60.468704],
                        [132.341756, 60.47197],
                        [132.34419, 60.478656],
                        [132.351313, 60.482069],
                        [132.348342, 60.487608],
                        [132.352966, 60.489947],
                        [132.353792, 60.494737],
                        [132.357671, 60.497844],
                        [132.351606, 60.503264],
                        [132.350663, 60.506898],
                        [132.346403, 60.511127],
                        [132.369332, 60.514898],
                        [132.375905, 60.518797],
                        [132.378327, 60.523218],
                        [132.387226, 60.524233],
                        [132.395511, 60.529631],
                        [132.406708, 60.533468],
                        [132.4267, 60.534086],
                        [132.44267, 60.537788],
                        [132.446813, 60.543535],
                        [132.45805, 60.546756],
                        [132.456243, 60.551879],
                        [132.450854, 60.555858],
                        [132.451645, 60.559751],
                        [132.45689, 60.566802],
                        [132.454072, 60.574126],
                        [132.464297, 60.578284],
                        [132.476128, 60.59214],
                        [132.468782, 60.59727],
                        [132.475535, 60.601357],
                        [132.474825, 60.604846],
                        [132.482336, 60.623943],
                        [132.491878, 60.624052],
                        [132.501538, 60.626759],
                        [132.510923, 60.622675],
                        [132.52129, 60.622004],
                        [132.538819, 60.627501],
                        [132.548515, 60.625975],
                        [132.563787, 60.626707],
                        [132.573197, 60.619935],
                        [132.59145, 60.618926],
                        [132.600431, 60.615188],
                        [132.614914, 60.6139],
                        [132.626981, 60.60347],
                        [132.646093, 60.602909],
                        [132.669795, 60.599015],
                        [132.684335, 60.600046],
                        [132.695849, 60.592175],
                        [132.710372, 60.590373],
                        [132.722611, 60.590992],
                        [132.729826, 60.586189],
                        [132.733266, 60.578516],
                        [132.747668, 60.575029],
                        [132.777385, 60.579851],
                        [132.782174, 60.582082],
                        [132.786201, 60.587676],
                        [132.793609, 60.591352],
                        [132.812916, 60.592721],
                        [132.825111, 60.588046],
                        [132.834215, 60.586631],
                        [132.841418, 60.588241],
                        [132.853135, 60.594462],
                        [132.863729, 60.596912],
                        [132.867661, 60.599506],
                        [132.866442, 60.608104],
                        [132.872591, 60.614684],
                        [132.891322, 60.61936],
                        [132.892973, 60.623996],
                        [132.905603, 60.627366],
                        [132.914785, 60.63387],
                        [132.932112, 60.635051],
                        [132.942013, 60.640383],
                        [132.943204, 60.641731],
                        [132.942285, 60.64288],
                        [132.93616, 60.645338],
                        [132.932543, 60.650714],
                        [132.934133, 60.651504],
                        [132.964286, 60.654501],
                        [132.981106, 60.647967],
                        [132.992683, 60.647158],
                        [133.006549, 60.651972],
                        [133.010396, 60.662534],
                        [133.035429, 60.666165],
                        [133.052355, 60.665019],
                        [133.066733, 60.673921],
                        [133.084484, 60.671759],
                        [133.091408, 60.677712],
                        [133.097245, 60.685667],
                        [133.122725, 60.696587],
                        [133.127614, 60.700307],
                        [133.12597, 60.704864],
                        [133.129266, 60.707866],
                        [133.128815, 60.714929],
                        [133.130549, 60.718705],
                        [133.127665, 60.721248],
                        [133.135703, 60.731435],
                        [133.147481, 60.734302],
                        [133.142831, 60.7406],
                        [133.141671, 60.749431],
                        [133.146507, 60.757244],
                        [133.146658, 60.757966],
                        [133.147699, 60.763014],
                        [133.15533, 60.768307],
                        [133.151938, 60.77543],
                        [133.157299, 60.777966],
                        [133.160637, 60.782071],
                        [133.144182, 60.786963],
                        [133.139134, 60.794705],
                        [133.141272, 60.7971],
                        [133.141147, 60.8],
                        [133.136568, 60.801912],
                        [133.137953, 60.806384],
                        [133.145869, 60.811183],
                        [133.145798, 60.815961],
                        [133.147512, 60.816799],
                        [133.14614, 60.818225],
                        [133.156951, 60.826243],
                        [133.161118, 60.832409],
                        [133.162055, 60.838073],
                        [133.16019, 60.84397],
                        [133.151826, 60.856054],
                        [133.146947, 60.866762],
                        [133.135089, 60.872048],
                        [133.133591, 60.876713],
                        [133.121509, 60.881859],
                        [133.119611, 60.886032],
                        [133.112185, 60.892896],
                        [133.110716, 60.89704],
                        [133.114343, 60.902117],
                        [133.112416, 60.90582],
                        [133.113047, 60.907866],
                        [133.125981, 60.913342],
                        [133.128704, 60.916698],
                        [133.127794, 60.91767],
                        [133.121042, 60.921138],
                        [133.122912, 60.926805],
                        [133.108617, 60.935946],
                        [133.10238, 60.945391],
                        [133.09981, 60.94686],
                        [133.098892, 60.948946],
                        [133.100535, 60.955467],
                        [133.089873, 60.959833],
                        [133.087068, 60.965075],
                        [133.085637, 60.974901],
                        [133.079996, 60.982066],
                        [133.080186, 60.993194],
                        [133.078369, 61.00017],
                        [133.075027, 61.00358],
                        [133.080978, 61.005446],
                        [133.079632, 61.013086],
                        [133.084631, 61.018416],
                        [133.087421, 61.026231],
                        [133.08451, 61.030255],
                        [133.077998, 61.031775],
                        [133.07382, 61.038925999999996],
                        [133.073318, 61.04486],
                        [133.065505, 61.048775],
                        [133.072843, 61.049915],
                        [133.078489, 61.056308],
                        [133.07525, 61.064101],
                        [133.075376, 61.067556],
                        [133.069399, 61.07072],
                        [133.067152, 61.075465],
                        [133.075028, 61.081564],
                        [133.070212, 61.086289],
                        [133.072688, 61.089696],
                        [133.070316, 61.096427],
                        [133.074483, 61.101582],
                        [133.076722, 61.108925],
                        [133.079532, 61.111037],
                        [133.080462, 61.116453],
                        [133.0934, 61.119573],
                        [133.095148, 61.121442],
                        [133.08851, 61.125334],
                        [133.08624, 61.131004],
                        [133.091197, 61.141741],
                        [133.09059, 61.144283],
                        [133.079422, 61.152141],
                        [133.077632, 61.156883],
                        [133.068731, 61.160565],
                        [133.068759, 61.164608],
                        [133.065388, 61.167991],
                        [133.071587, 61.17454],
                        [133.072509, 61.179101],
                        [133.072691, 61.180986],
                        [133.067939, 61.187676],
                        [133.0743, 61.196801],
                        [133.071524, 61.200512],
                        [133.076486, 61.20358],
                        [133.076934, 61.209102],
                        [133.079147, 61.212011],
                        [133.076781, 61.21809],
                        [133.083108, 61.226957],
                        [133.081651, 61.232503],
                        [133.083148, 61.237485],
                        [133.095711, 61.252082],
                        [133.100532, 61.260653],
                        [133.099572, 61.264207],
                        [133.097268, 61.26883],
                        [133.094219, 61.269299],
                        [133.092749, 61.273511],
                        [133.090473, 61.273747],
                        [133.091339, 61.278381],
                        [133.089607, 61.283556],
                        [133.093023, 61.290688],
                        [133.090026, 61.295821],
                        [133.09271, 61.301691],
                        [133.086262, 61.310195],
                        [133.086229, 61.323217],
                        [133.076923, 61.339365],
                        [133.073118, 61.340741],
                        [133.066377, 61.354049],
                        [133.061352, 61.358706],
                        [133.052434, 61.374224],
                        [133.047095, 61.378648],
                        [133.050581, 61.384271],
                        [133.064883, 61.39126],
                        [133.069166, 61.398298],
                        [133.070369, 61.403514],
                        [133.059084, 61.407862],
                        [133.056123, 61.413222],
                        [133.045195, 61.414487],
                        [133.038392, 61.425863],
                        [133.048275, 61.429294],
                        [133.072708, 61.44254],
                        [133.069143, 61.448055],
                        [133.063119, 61.450772],
                        [133.068109, 61.456529],
                        [133.074274, 61.458403],
                        [133.069114, 61.46223],
                        [133.068149, 61.468227],
                        [133.071453, 61.472458],
                        [133.068802, 61.475507],
                        [133.067574, 61.480242],
                        [133.062401, 61.485571],
                        [133.062948, 61.489072],
                        [133.059824, 61.492845],
                        [133.060527, 61.495211],
                        [133.065917, 61.499501],
                        [133.065701, 61.501232],
                        [133.059044, 61.506725],
                        [133.05821, 61.509191],
                        [133.046785, 61.511228],
                        [133.042083, 61.519581],
                        [133.033212, 61.522332],
                        [133.031545, 61.528874],
                        [133.027233, 61.532467],
                        [133.031817, 61.538017],
                        [133.03081, 61.543161],
                        [133.026629, 61.54907],
                        [133.014295, 61.556752]
                    ]
                ]
            },
            "properties": {
                "id": 4,
                "color": "#000099",
                "": "",
                "desc": "       (),   .     -          ...",
                "oktmo": "98608000",
                "raion": null,
                "population": 0,
                "square": 29404175850.1543,
                "url": "<a href='/raion/details/4'></a>"
            }
        }
    ]
}
